soykeyword/__init__.py
soykeyword/utils.py
soykeyword/lasso/__init__.py
soykeyword/lasso/_lasso.py
soykeyword/proportion/__init__.py
soykeyword/proportion/_proportion.py
soykeyword-0.0.14.dist-info/METADATA
soykeyword-0.0.14.dist-info/RECORD
soykeyword-0.0.14.dist-info/WHEEL
soykeyword-0.0.14.dist-info/top_level.txt
