Metadata-Version: 2.1
Name: soykeyword
Version: 0.0.14
Summary: Unsupervised Keyword Extracters
Home-page: https://github.com/lovit/soykeyword
Author: Lovit
Author-email: soy.lovit@gmail.com
License: UNKNOWN
Platform: UNKNOWN
Classifier: Programming Language :: Python :: 3.6
Classifier: License :: OSI Approved :: GNU General Public License v3 (GPLv3)
Classifier: Operating System :: OS Independent
Requires-Dist: numpy (>=1.12.0)
Requires-Dist: scikit-learn (>=0.18.0)
Requires-Dist: psutil (>=5.0.1)
